senaite.core-1.2.8.2-py2.7-nspkg.pth
bika/lims/__init__.py
bika/lims/barcode.py
bika/lims/config.py
bika/lims/configure.zcml
bika/lims/decorators.py
bika/lims/fields.py
bika/lims/idserver.py
bika/lims/numbergenerator.py
bika/lims/overrides.zcml
bika/lims/permissions.py
bika/lims/permissions.txt
bika/lims/permissions.zcml
bika/lims/profiles.zcml
bika/lims/search.py
bika/lims/search.zcml
bika/lims/setuphandlers.py
bika/lims/testing.py
bika/lims/validators.py
bika/lims/adapters/__init__.py
bika/lims/adapters/acquirefielddefaults.py
bika/lims/adapters/configure.zcml
bika/lims/adapters/identifiers.py
bika/lims/adapters/referencewidgetvocabulary.py
bika/lims/adapters/stickers.py
bika/lims/adapters/widgetvisibility.py
bika/lims/api/__init__.py
bika/lims/api/analysis.py
bika/lims/browser/__init__.py
bika/lims/browser/accreditation.py
bika/lims/browser/analysis.py
bika/lims/browser/analysis.zcml
bika/lims/browser/analysisprofile.py
bika/lims/browser/analysisprofile.zcml
bika/lims/browser/analysisservice.py
bika/lims/browser/analysisservice.zcml
bika/lims/browser/analysisspec.py
bika/lims/browser/analysisspec.zcml
bika/lims/browser/arimports.py
bika/lims/browser/arimports.zcml
bika/lims/browser/artemplate.py
bika/lims/browser/artemplate.zcml
bika/lims/browser/attachment.py
bika/lims/browser/attachment.zcml
bika/lims/browser/batchfolder.py
bika/lims/browser/batchfolder.zcml
bika/lims/browser/bika_listing.py
bika/lims/browser/bika_listing.zcml
bika/lims/browser/bika_listing_filter_bar.py
bika/lims/browser/calcs.py
bika/lims/browser/calcs.zcml
bika/lims/browser/clientfolder.py
bika/lims/browser/clientfolder.zcml
bika/lims/browser/configure.zcml
bika/lims/browser/contact.py
bika/lims/browser/contact.zcml
bika/lims/browser/contentmenu.py
bika/lims/browser/header_table.py
bika/lims/browser/instrument.py
bika/lims/browser/instrument.zcml
bika/lims/browser/instrumentlocation.py
bika/lims/browser/instrumentlocation.zcml
senaite.core-1.2.8.2.dist-info/METADATA
senaite.core-1.2.8.2.dist-info/RECORD
senaite.core-1.2.8.2.dist-info/WHEEL
senaite.core-1.2.8.2.dist-info/entry_points.txt
senaite.core-1.2.8.2.dist-info/namespace_packages.txt
senaite.core-1.2.8.2.dist-info/top_level.txt
