Metadata-Version: 2.1
Name: senaite.core
Version: 1.2.8.2
Summary: SENAITE Core
Home-page: https://github.com/senaite/senaite.core
Author: SENAITE Foundation
Author-email: support@senaite.com
License: GPLv2
Keywords: senaite,lims,opensource
Platform: UNKNOWN
Classifier: Development Status :: 5 - Production/Stable
Classifier: Environment :: Web Environment
Classifier: Framework :: Plone
Classifier: Framework :: Zope2
Classifier: Programming Language :: Python
Provides-Extra: test
Requires-Dist: setuptools
Requires-Dist: plone.api
Requires-Dist: plone.subrequest
Requires-Dist: plone.jsonapi.core
Requires-Dist: Products.ATExtensions (>=1.1a3)
Requires-Dist: Products.CMFEditions
Requires-Dist: Products.DataGridField
Requires-Dist: Products.AdvancedQuery
Requires-Dist: Products.TinyMCE
Requires-Dist: Products.TextIndexNG3
Requires-Dist: collective.monkeypatcher
Requires-Dist: collective.js.jqueryui
Requires-Dist: plone.app.z3cform
Requires-Dist: openpyxl (==1.5.8)
Requires-Dist: plone.app.iterate
Requires-Dist: magnitude
Requires-Dist: gpw
Requires-Dist: jarn.jsi18n
Requires-Dist: WeasyPrint
Requires-Dist: collective.progressbar
Requires-Dist: z3c.unconfigure (==1.0.1)
Requires-Dist: plone.app.dexterity
Requires-Dist: plone.app.relationfield
Requires-Dist: plone.app.referenceablebehavior
Requires-Dist: five.pt (==2.2.4)
Requires-Dist: z3c.jbot
Requires-Dist: plone.resource
Requires-Dist: CairoSVG (==1.0.20)
Requires-Dist: collective.taskqueue
Requires-Dist: zopyx.txng3.ext (==3.4.0)
Provides-Extra: test
Requires-Dist: unittest2; extra == 'test'
Requires-Dist: plone.app.testing; extra == 'test'
